{
  "id": "events",
  "type": "SharedSlice",
  "name": "Events",
  "description": "Events",
  "variations": [
    {
      "id": "default",
      "name": "Default",
      "docURL": "...",
      "version": "initial",
      "description": "Default",
      "imageUrl": "",
      "primary": {
        "title": {
          "type": "Text",
          "config": {
            "label": "Title",
            "placeholder": ""
          }
        },
        "google": {
          "type": "Text",
          "config": {
            "label": "Google",
            "placeholder": ""
          }
        },
        "google_text": {
          "type": "Text",
          "config": {
            "label": "Google Text",
            "placeholder": ""
          }
        },
        "instagram": {
          "type": "Text",
          "config": {
            "label": "Instagram",
            "placeholder": ""
          }
        },
        "instagram_texte": {
          "type": "Text",
          "config": {
            "label": "Instagram Text",
            "placeholder": ""
          }
        },
        "facebook": {
          "type": "Text",
          "config": {
            "label": "Facebook",
            "placeholder": ""
          }
        },
        "facebook_texte": {
          "type": "Text",
          "config": {
            "label": "Facebook Text",
            "placeholder": ""
          }
        }
      },
      "items": {}
    }
  ]
}